lyceeplus.py
lyceeplus-0.1.2.dist-info/WHEEL
lyceeplus-0.1.2.dist-info/METADATA
lyceeplus-0.1.2.dist-info/RECORD
