Metadata-Version: 2.1
Name: lyceeplus
Version: 0.1.2
Summary: 
Author: Pierre Lemaitre
Author-email: oultetman@sfr.fr
Requires-Python: >=3.8,<4.0
Classifier: Programming Language :: Python :: 3
Classifier: Programming Language :: Python :: 3.10
Classifier: Programming Language :: Python :: 3.8
Classifier: Programming Language :: Python :: 3.9
Requires-Dist: matplotlib (>=3.7.0,<4.0.0)
Requires-Dist: numpy (>=1.24.2,<2.0.0)
